sheetpicturefinder/__init__.py
sheetpicturefinder/xlsx_picture_finder.py
sheetpicturefinder-1.1.3.dist-info/LICENSE
sheetpicturefinder-1.1.3.dist-info/METADATA
sheetpicturefinder-1.1.3.dist-info/WHEEL
sheetpicturefinder-1.1.3.dist-info/top_level.txt
sheetpicturefinder-1.1.3.dist-info/RECORD
