Metadata-Version: 2.1
Name: sheetpicturefinder
Version: 1.1.3
Summary: SheetPictureFinder is a pure Python utility for extracting images from Excel .xlsx files — specifically from worksheets and cell addresses. It parses the internal XML structure of Excel files and maps embedded images to their anchor locations.
Author-email: Samprit Sarkar <samprits5@gmail.com>
License: MIT
Project-URL: Homepage, https://github.com/samprits5/
Requires-Python: <3.10,>=3.8
License-File: LICENSE
Requires-Dist: Pillow==10.3.0
